birdseye/__init__.py
birdseye/__main__.py
birdseye/bird.py
birdseye/clear_db.py
birdseye/db.py
birdseye/import_hook.py
birdseye/ipython.py
birdseye/server.py
birdseye/trace_module.py
birdseye/trace_module_deep.py
birdseye/tracer.py
birdseye/utils.py
birdseye/version.py
birdseye/static/favicon.ico
birdseye/static/css/bootstrap.min.css
birdseye/static/css/hljs.min.css
birdseye/static/css/jquery-ui.min.css
birdseye/static/css/main.css
birdseye/static/css/proton/30px.png
birdseye/static/css/proton/32px.png
birdseye/static/css/proton/style.css
birdseye/static/css/proton/style.min.css
birdseye/static/css/proton/throbber.gif
birdseye/static/css/proton/fonts/titillium/titilliumweb-bold-webfont.eot
birdseye/static/css/proton/fonts/titillium/titilliumweb-bold-webfont.svg
birdseye/static/css/proton/fonts/titillium/titilliumweb-bold-webfont.ttf
birdseye/static/css/proton/fonts/titillium/titilliumweb-bold-webfont.woff
birdseye/static/css/proton/fonts/titillium/titilliumweb-extralight-webfont.eot
birdseye/static/css/proton/fonts/titillium/titilliumweb-extralight-webfont.svg
birdseye/static/css/proton/fonts/titillium/titilliumweb-extralight-webfont.ttf
birdseye/static/css/proton/fonts/titillium/titilliumweb-extralight-webfont.woff
birdseye/static/css/proton/fonts/titillium/titilliumweb-regular-webfont.eot
birdseye/static/css/proton/fonts/titillium/titilliumweb-regular-webfont.svg
birdseye/static/css/proton/fonts/titillium/titilliumweb-regular-webfont.ttf
birdseye/static/css/proton/fonts/titillium/titilliumweb-regular-webfont.woff
birdseye/static/fonts/glyphicons-halflings-regular.eot
birdseye/static/fonts/glyphicons-halflings-regular.svg
birdseye/static/fonts/glyphicons-halflings-regular.ttf
birdseye/static/fonts/glyphicons-halflings-regular.woff
birdseye/static/fonts/glyphicons-halflings-regular.woff2
birdseye/static/img/handle.png
birdseye/static/img/logo.png
birdseye/static/img/type_icons/NoneType.png
birdseye/static/img/type_icons/complex.png
birdseye-0.10.0.dist-info/licenses/LICENSE.txt
birdseye-0.10.0.dist-info/METADATA
birdseye-0.10.0.dist-info/WHEEL
birdseye-0.10.0.dist-info/entry_points.txt
birdseye-0.10.0.dist-info/top_level.txt
birdseye-0.10.0.dist-info/RECORD
