Metadata-Version: 2.4
Name: birdseye
Version: 0.10.0
Summary: Graphical Python debugger which lets you easily view the values of all evaluated expressions
Home-page: http://github.com/alexmojaki/birdseye
Author: Alex Hall
Author-email: alex.mojaki@gmail.com
License: MIT
Classifier: Intended Audience :: Developers
Classifier: Programming Language :: Python
Classifier: Programming Language :: Python :: 3
Classifier: Programming Language :: Python :: 3.8
Classifier: Programming Language :: Python :: 3.9
Classifier: Programming Language :: Python :: 3.10
Classifier: Programming Language :: Python :: 3.11
Classifier: Programming Language :: Python :: 3.12
Classifier: Programming Language :: Python :: 3.13
Classifier: License :: OSI Approved :: MIT License
Classifier: Operating System :: OS Independent
Classifier: Topic :: Software Development :: Debuggers
Requires-Python: >=3.8
License-File: LICENSE.txt
Requires-Dist: Flask
Requires-Dist: flask-humanize
Requires-Dist: sqlalchemy
Requires-Dist: asttokens
Requires-Dist: littleutils>=0.2
Requires-Dist: cheap_repr
Requires-Dist: outdated
Requires-Dist: cached_property
Provides-Extra: tests
Requires-Dist: bs4; extra == "tests"
Requires-Dist: selenium; extra == "tests"
Requires-Dist: pytest; extra == "tests"
Requires-Dist: numpy; extra == "tests"
Requires-Dist: pandas; extra == "tests"
Requires-Dist: gunicorn; extra == "tests"
Requires-Dist: twine; extra == "tests"
Requires-Dist: build; extra == "tests"
Requires-Dist: django; extra == "tests"
Requires-Dist: IPython; extra == "tests"
Dynamic: license-file
